geecrack.py
geecrack-1.0.0.dist-info/METADATA
geecrack-1.0.0.dist-info/WHEEL
geecrack-1.0.0.dist-info/top_level.txt
geecrack-1.0.0.dist-info/RECORD
